token_calculator/__init__.py
token_calculator/alerts.py
token_calculator/context_analyzer.py
token_calculator/conversation_manager.py
token_calculator/cost_calculator.py
token_calculator/cost_tracker.py
token_calculator/forecasting.py
token_calculator/health_monitor.py
token_calculator/model_selector.py
token_calculator/models.py
token_calculator/optimizer.py
token_calculator/storage.py
token_calculator/tokenizer.py
token_calculator/workflow_tracker.py
token_calculator/integrations/__init__.py
token_calculator/integrations/langchain.py
token_calculator-2.1.0.dist-info/licenses/LICENSE
token_calculator-2.1.0.dist-info/METADATA
token_calculator-2.1.0.dist-info/WHEEL
token_calculator-2.1.0.dist-info/top_level.txt
token_calculator-2.1.0.dist-info/RECORD
